Metadata-Version: 2.4
Name: agentMET4FOF
Version: 0.13.4
Summary: A software package for the integration of metrological input into an agent-based system for the consideration of measurement uncertainty in current industrial manufacturing processes.
Home-page: https://github.com/Met4FoF/agentMET4FOF
Download-URL: https://github.com/Met4FoF/agentMET4FOF/releases/download/v0.13.4/agentMET4FOF-0.13.4.tar.gz
Author: Bang Xiang Yong, Björn Ludwig, Anupam Prasad Vedurmudi, Maximilian Gruber, Haris Lulic
Author-email: bxy20@cam.ac.uk
Project-URL: Documentation, https://agentmet4fof.readthedocs.io/en/v0.13.4/
Project-URL: Source, https://github.com/Met4FoF/agentMET4FOF/tree/v0.13.4/
Project-URL: Tracker, https://github.com/Met4FoF/agentMET4FOF/issues
Keywords: uncertainty metrology MAS agent-based agents
Classifier: Development Status :: 4 - Beta
Classifier: Topic :: Utilities
Classifier: Topic :: Scientific/Engineering
Classifier: Topic :: Software Development :: Libraries :: Python Modules
Classifier: Intended Audience :: Education
Classifier: Intended Audience :: Science/Research
Classifier: License :: OSI Approved :: GNU Lesser General Public License v3 (LGPLv3)
Classifier: Programming Language :: Python :: 3
Classifier: Programming Language :: Python :: 3.8
Classifier: Programming Language :: Python :: 3.9
Classifier: Programming Language :: Python :: 3.10
Classifier: Programming Language :: Python :: 3.11
Classifier: Operating System :: OS Independent
Requires-Python: >=3.8
Requires-Dist: numpy
Requires-Dist: scipy
Requires-Dist: matplotlib
Requires-Dist: pandas
Requires-Dist: osbrain
Requires-Dist: dash
Requires-Dist: dash_cytoscape
Requires-Dist: networkx
Requires-Dist: plotly
Requires-Dist: time-series-buffer
Requires-Dist: time-series-metadata
Requires-Dist: mpld3
Requires-Dist: mesa
Requires-Dist: multiprocess
Requires-Dist: visdcc
Provides-Extra: tutorials
Requires-Dist: notebook; extra == "tutorials"
Requires-Dist: PyDynamic; extra == "tutorials"
Provides-Extra: dev
Requires-Dist: black[jupyter]; extra == "dev"
Requires-Dist: pytest; extra == "dev"
Requires-Dist: pytest-cov; extra == "dev"
Requires-Dist: pytest-timeout; extra == "dev"
Requires-Dist: pywin32; platform_system == "Windows" and extra == "dev"
Requires-Dist: pywin32-ctypes; platform_system == "Windows" and extra == "dev"
Requires-Dist: pywinpty; platform_system == "Windows" and extra == "dev"
Requires-Dist: requests; extra == "dev"
Requires-Dist: psutil; extra == "dev"
Requires-Dist: sphinx; extra == "dev"
Requires-Dist: nbsphinx; extra == "dev"
Requires-Dist: recommonmark; extra == "dev"
Requires-Dist: sphinx_rtd_theme; extra == "dev"
Requires-Dist: ipython; extra == "dev"
Requires-Dist: tox; extra == "dev"
Requires-Dist: python-semantic-release<8; extra == "dev"
Requires-Dist: hypothesis; extra == "dev"
Provides-Extra: docs
Requires-Dist: sphinx; extra == "docs"
Requires-Dist: nbsphinx; extra == "docs"
Requires-Dist: recommonmark; extra == "docs"
Requires-Dist: sphinx_rtd_theme; extra == "docs"
Requires-Dist: ipython; extra == "docs"
Requires-Dist: docutils; extra == "docs"
Dynamic: author
Dynamic: author-email
Dynamic: classifier
Dynamic: description
Dynamic: description-content-type
Dynamic: download-url
Dynamic: home-page
Dynamic: keywords
Dynamic: project-url
Dynamic: provides-extra
Dynamic: requires-dist
Dynamic: requires-python
Dynamic: summary
